{
    "nowTime": "16:09:07",
    "products": [
        {
            "id": 25,
            "title": "Gulab Powder 50 Gram"
        },
        {
            "id": 26,
            "title": "Plant Hanger For Home"
        },
        {
            "id": 27,
            "title": "Flying Wooden Bird"
        },
        {
            "id": 28,
            "title": "3D Embellishment Art Lamp"
        },
        {
            "id": 29,
            "title": "Handcraft Chinese style"
        },
        {
            "id": 30,
            "title": "Key Holder"
        }
    ]
}